LICENSE
README.md
setup.py
probuster/__init__.py
probuster/probuster.py
probuster.egg-info/PKG-INFO
probuster.egg-info/SOURCES.txt
probuster.egg-info/dependency_links.txt
probuster.egg-info/entry_points.txt
probuster.egg-info/requires.txt
probuster.egg-info/top_level.txt
probuster/modules/__init__.py
probuster/modules/probuster_documentation.py
probuster/modules/banner/__init__.py
probuster/modules/banner/banner.py
probuster/modules/dir/__init__.py
probuster/modules/dir/dir.py
probuster/modules/dnb/__init__.py
probuster/modules/dnb/dnb.py
probuster/modules/version/__init__.py
probuster/modules/version/version.py
probuster/modules/vhost/__init__.py
probuster/modules/vhost/vhost.py
probuster/modules/wordlist/__init__.py
probuster/modules/wordlist/wordlist.py