Metadata-Version: 2.1
Name: probuster
Version: 1.0.2
Summary:  A Python based Web Application Penetration testing tool for Information Gathering and Content Discovery
Author: D. Sanjai Kumar
Author-email: bughunterz0047@gmail.com
License-File: LICENSE
Requires-Dist: alive_progress>=3.1.4
Requires-Dist: art>=6.1
Requires-Dist: beautifulsoup4>=4.11.1
Requires-Dist: colorama>=0.4.4
Requires-Dist: httpx>=0.26.0
Requires-Dist: Requests>=2.31.0
Requires-Dist: rich>=13.7.0
Requires-Dist: urllib3>=1.26.18
Requires-Dist: streamlit>=1.29.0
Requires-Dist: aiofiles>=23.2.1
Requires-Dist: aiohttp>=3.8.6
Requires-Dist: asyncio>=3.4.3
Requires-Dist: h11==0.13.0
Requires-Dist: anyio>=4.2.0
Requires-Dist: aiodnsresolver>=0.0.155
Requires-Dist: click>=8.1.7
